connsearch/__init__.py
connsearch/components.py
connsearch/connsearcher.py
connsearch/corrsim.py
connsearch/crossval.py
connsearch/utils.py
connsearch/permute/__init__.py
connsearch/permute/perm_manager.py
connsearch/permute/shuffle.py
connsearch/report/__init__.py
connsearch/report/plots.py
connsearch/report/tables.py
connsearch-0.1.1.dist-info/LICENSE
connsearch-0.1.1.dist-info/METADATA
connsearch-0.1.1.dist-info/WHEEL
connsearch-0.1.1.dist-info/top_level.txt
connsearch-0.1.1.dist-info/RECORD
