Metadata-Version: 2.1
Name: connsearch
Version: 0.1.1
Summary: Analysis of connectivity data by dividing the connectome and fitting independent models
Home-page: https://github.com/paulcbogdan/ConnSearch-Package
Author: paulcbogdan
Author-email: paulcbogdan@gmail.com
License: MIT
Keywords: fmri,connectivity,multivariate,machine learning
Requires-Python: >=3.5
License-File: LICENSE
Requires-Dist: scikit-learn
Requires-Dist: numpy
Requires-Dist: nilearn
Requires-Dist: setuptools
Requires-Dist: matplotlib
Requires-Dist: nichord
Requires-Dist: tqdm
Requires-Dist: pandas
Requires-Dist: scipy
Requires-Dist: statsmodels
